modis_sinusoidal_tile_converter/__init__.py
modis_sinusoidal_tile_converter/constant.py
modis_sinusoidal_tile_converter/convert.py
modis_sinusoidal_tile_converter/renderer.py
modis_sinusoidal_tile_converter/sinusoidal.py
modis_sinusoidal_tile_converter/webmercator.py
modis_sinusoidal_tile_converter-2.0.5.dist-info/licenses/LICENSE
modis_sinusoidal_tile_converter-2.0.5.dist-info/METADATA
modis_sinusoidal_tile_converter-2.0.5.dist-info/WHEEL
modis_sinusoidal_tile_converter-2.0.5.dist-info/top_level.txt
modis_sinusoidal_tile_converter-2.0.5.dist-info/RECORD
