Metadata-Version: 2.4
Name: modis_sinusoidal_tile_converter
Version: 2.0.5
Summary:  A simple Python tool for converting geographic coordinates into MODIS (Moderate-Resolution Imaging Spectroradiometer) tile numbers.
License: GNU GENERAL PUBLIC LICENSE
Classifier: Development Status :: 3 - Alpha
Classifier: Programming Language :: Python :: 3.9
Classifier: Intended Audience :: Developers
Classifier: Operating System :: MacOS
Classifier: Operating System :: POSIX :: Linux
Classifier: Operating System :: Microsoft :: Windows
Requires-Python: >=3.6
License-File: LICENSE
Requires-Dist: pyproj
Dynamic: license-file
